ciallociallo/__main__.py
ciallociallo/check_sysinfo.py
ciallociallo/cli.py
ciallociallo/play.py
ciallociallo/set_title.py
ciallociallo/txt_frames/amane/w100/a0.3.cap
ciallociallo/txt_frames/amane/w100/a0.4.cap
ciallociallo/txt_frames/amane/w100/a0.5.cap
ciallociallo/txt_frames/amane/w100/a0.55.cap
ciallociallo/txt_frames/amane/w100/a0.6.cap
ciallociallo/txt_frames/amane/w100/a0.7.cap
ciallociallo/txt_frames/amane/w110/a0.3.cap
ciallociallo/txt_frames/amane/w110/a0.4.cap
ciallociallo/txt_frames/amane/w110/a0.5.cap
ciallociallo/txt_frames/amane/w110/a0.55.cap
ciallociallo/txt_frames/amane/w110/a0.6.cap
ciallociallo/txt_frames/amane/w110/a0.7.cap
ciallociallo/txt_frames/amane/w120/a0.3.cap
ciallociallo/txt_frames/amane/w120/a0.4.cap
ciallociallo/txt_frames/amane/w120/a0.5.cap
ciallociallo/txt_frames/amane/w120/a0.55.cap
ciallociallo/txt_frames/amane/w120/a0.6.cap
ciallociallo/txt_frames/amane/w120/a0.7.cap
ciallociallo/txt_frames/amane/w130/a0.3.cap
ciallociallo/txt_frames/amane/w130/a0.4.cap
ciallociallo/txt_frames/amane/w130/a0.5.cap
ciallociallo/txt_frames/amane/w130/a0.55.cap
ciallociallo/txt_frames/amane/w130/a0.6.cap
ciallociallo/txt_frames/amane/w130/a0.7.cap
ciallociallo/txt_frames/amane/w140/a0.3.cap
ciallociallo/txt_frames/amane/w140/a0.4.cap
ciallociallo/txt_frames/amane/w140/a0.5.cap
ciallociallo/txt_frames/amane/w140/a0.55.cap
ciallociallo/txt_frames/amane/w140/a0.6.cap
ciallociallo/txt_frames/amane/w140/a0.7.cap
ciallociallo/txt_frames/amane/w150/a0.3.cap
ciallociallo/txt_frames/amane/w150/a0.4.cap
ciallociallo/txt_frames/amane/w150/a0.5.cap
ciallociallo/txt_frames/amane/w150/a0.55.cap
ciallociallo/txt_frames/amane/w150/a0.6.cap
ciallociallo/txt_frames/amane/w150/a0.7.cap
ciallociallo/txt_frames/amane/w70/a0.3.cap
ciallociallo/txt_frames/amane/w70/a0.4.cap
ciallociallo/txt_frames/amane/w70/a0.5.cap
ciallociallo/txt_frames/amane/w70/a0.55.cap
ciallociallo/txt_frames/amane/w70/a0.6.cap
ciallociallo/txt_frames/amane/w70/a0.7.cap
ciallociallo-0.1.2.dist-info/licenses/LICENSE
ciallociallo-0.1.2.dist-info/METADATA
ciallociallo-0.1.2.dist-info/WHEEL
ciallociallo-0.1.2.dist-info/entry_points.txt
ciallociallo-0.1.2.dist-info/top_level.txt
ciallociallo-0.1.2.dist-info/RECORD
