Metadata-Version: 2.4
Name: ciallociallo
Version: 0.1.2
Summary: Ciallo~(∠・ω< )⌒★ This is a CLI ASCII animation screensaver.
Author-email: Nerovix <nerovix@foxmail.com>
License: MIT
Project-URL: Homepage, https://github.com/Nerovix/ciallociallo
Project-URL: Issues, https://github.com/Nerovix/ciallociallo/issues
Classifier: Programming Language :: Python :: 3
Classifier: License :: OSI Approved :: MIT License
Classifier: Operating System :: OS Independent
Classifier: Environment :: Console
Requires-Python: >=3.8
License-File: LICENSE
Requires-Dist: importlib-resources>=5.12; python_version < "3.9"
Requires-Dist: windows-curses; platform_system == "Windows"
Provides-Extra: dev
Requires-Dist: build; extra == "dev"
Requires-Dist: twine; extra == "dev"
Dynamic: license-file
